{
  "video_id": "9LvdPzg8pFg",
  "title": "【#歌枠】深夜のしっとり歌配信♬singing stream【儚牙紺】",
  "start_datetime": "2023-05-28T04:33:51Z",
  "thumbnail_url": "https://i.ytimg.com/vi/9LvdPzg8pFg/maxresdefault.jpg",
  "timestamps": [
    {
      "time": 288,
      "original_time": "0:04:48",
      "song_id": "SjTwZ5snfU-",
      "comment_source": "comment",
      "comment_date": "2023-05-27T16:44:49Z"
    },
    {
      "time": 631,
      "original_time": "0:10:31",
      "song_id": "nGV2VDfEdMf",
      "comment_source": "comment",
      "comment_date": "2023-05-27T16:44:49Z"
    },
    {
      "time": 1021,
      "original_time": "0:17:01",
      "song_id": "uxwmNsEgw8l",
      "comment_source": "comment",
      "comment_date": "2023-05-27T16:44:49Z"
    },
    {
      "time": 1421,
      "original_time": "0:23:41",
      "song_id": "rJ7EIZGSW6W",
      "comment_source": "comment",
      "comment_date": "2023-05-27T16:44:49Z"
    },
    {
      "time": 1882,
      "original_time": "0:31:22",
      "song_id": "JBE6svZmeMj",
      "comment_source": "comment",
      "comment_date": "2023-05-27T16:44:49Z"
    },
    {
      "time": 2557,
      "original_time": "0:42:37",
      "song_id": "HY7A6nlYymq",
      "comment_source": "comment",
      "comment_date": "2023-05-27T16:44:49Z"
    },
    {
      "time": 3091,
      "original_time": "0:51:31",
      "song_id": "EfvJFqy-L1Y",
      "comment_source": "comment",
      "comment_date": "2023-05-27T16:44:49Z"
    },
    {
      "time": 3603,
      "original_time": "1:00:03",
      "song_id": "0dTcpXqsiVD",
      "comment_source": "comment",
      "comment_date": "2023-05-27T16:44:49Z"
    },
    {
      "time": 4316,
      "original_time": "1:11:56",
      "song_id": "EO3WTX_Z4mo",
      "comment_source": "comment",
      "comment_date": "2023-05-27T16:44:49Z"
    }
  ]
}