{
  "video_id": "jL9M31Xll-c",
  "title": "【#歌枠コラボ】猫と狼と狐でセッション歌配信 / singing stream♪【新人Vtuber/儚牙紺】",
  "start_datetime": "2023-02-09T16:58:48Z",
  "thumbnail_url": "https://i.ytimg.com/vi/jL9M31Xll-c/maxresdefault.jpg",
  "timestamps": [
    {
      "time": 586,
      "original_time": "0:09:46",
      "song_id": "KNtBtoKepLS",
      "comment_source": "comment",
      "comment_date": "2023-02-09T16:25:49Z"
    },
    {
      "time": 1392,
      "original_time": "0:23:12",
      "song_id": "OrOrGJznKIQ",
      "comment_source": "comment",
      "comment_date": "2023-02-09T16:25:49Z"
    },
    {
      "time": 1986,
      "original_time": "0:33:06",
      "song_id": "lID4oF-ka-a",
      "comment_source": "comment",
      "comment_date": "2023-02-09T16:25:49Z"
    },
    {
      "time": 2422,
      "original_time": "0:40:22",
      "song_id": "nTZddcH-6pS",
      "comment_source": "comment",
      "comment_date": "2023-02-09T16:25:49Z"
    },
    {
      "time": 2900,
      "original_time": "0:48:20",
      "song_id": "3hoLDPGvuoq",
      "comment_source": "comment",
      "comment_date": "2023-02-09T16:25:49Z"
    },
    {
      "time": 3602,
      "original_time": "1:00:02",
      "song_id": "6Kfn6Rw2ms5",
      "comment_source": "comment",
      "comment_date": "2023-02-09T16:25:49Z"
    },
    {
      "time": 4086,
      "original_time": "1:08:06",
      "song_id": "edn3xBRQ9vg",
      "comment_source": "comment",
      "comment_date": "2023-02-09T16:25:49Z"
    },
    {
      "time": 4835,
      "original_time": "1:20:35",
      "song_id": "AXSxHpsxdFa",
      "comment_source": "comment",
      "comment_date": "2023-02-09T16:25:49Z"
    },
    {
      "time": 5613,
      "original_time": "1:33:33",
      "song_id": "5BUCvbVPysD",
      "comment_source": "comment",
      "comment_date": "2023-02-09T16:25:49Z"
    },
    {
      "time": 6203,
      "original_time": "1:43:23",
      "song_id": "vfb42PdqQ58",
      "comment_source": "comment",
      "comment_date": "2023-02-09T16:25:49Z"
    },
    {
      "time": 7028,
      "original_time": "1:57:08",
      "song_id": "MXLYDOB6wPR",
      "comment_source": "comment",
      "comment_date": "2023-02-09T16:25:49Z"
    },
    {
      "time": 8397,
      "original_time": "2:19:57",
      "song_id": "KH2n974gbE_",
      "comment_source": "comment",
      "comment_date": "2023-02-09T16:25:49Z"
    },
    {
      "time": 9479,
      "original_time": "2:37:59",
      "song_id": "thMsuTajMYS",
      "comment_source": "comment",
      "comment_date": "2023-02-09T16:25:49Z"
    },
    {
      "time": 10086,
      "original_time": "2:48:06",
      "song_id": "Bj0J8PfFsL5",
      "comment_source": "comment",
      "comment_date": "2023-02-09T16:25:49Z"
    },
    {
      "time": 10594,
      "original_time": "2:56:34",
      "song_id": "C84h_ucFYn6",
      "comment_source": "comment",
      "comment_date": "2023-02-09T16:25:49Z"
    },
    {
      "time": 10890,
      "original_time": "3:01:30",
      "song_id": "Q0Ad5zDBH5Q",
      "comment_source": "comment",
      "comment_date": "2023-02-09T16:25:49Z"
    }
  ]
}