{
  "video_id": "nyWoh62oOps",
  "title": "〔#歌枠┊KARAOKE〕新マイクお披露目するよ！１０月最初の歌枠 ଓ⊹ singing stream 〔#儚牙紺/Vtuber〕",
  "start_datetime": "2024-10-01T11:25:10Z",
  "thumbnail_url": "https://i.ytimg.com/vi/nyWoh62oOps/maxresdefault.jpg",
  "timestamps": [
    {
      "time": 493,
      "original_time": "0:08:13",
      "song_id": "7rTIMtOJmdZ",
      "comment_source": "comment",
      "comment_date": "2024-10-01T12:55:36Z"
    },
    {
      "time": 1025,
      "original_time": "0:17:05",
      "song_id": "rw0gUdvsEHw",
      "comment_source": "comment",
      "comment_date": "2024-10-01T12:55:36Z"
    },
    {
      "time": 1590,
      "original_time": "0:26:30",
      "song_id": "iJfrEEWbFDH",
      "comment_source": "comment",
      "comment_date": "2024-10-01T12:55:36Z"
    },
    {
      "time": 2261,
      "original_time": "0:37:41",
      "song_id": "KNtBtoKepLS",
      "comment_source": "comment",
      "comment_date": "2024-10-01T12:55:36Z"
    },
    {
      "time": 2718,
      "original_time": "0:45:18",
      "song_id": "EpDo9OA_Gyy",
      "comment_source": "comment",
      "comment_date": "2024-10-01T12:55:36Z"
    },
    {
      "time": 3224,
      "original_time": "0:53:44",
      "song_id": "uXXtUZ5N-8p",
      "comment_source": "comment",
      "comment_date": "2024-10-01T12:55:36Z"
    },
    {
      "time": 3729,
      "original_time": "1:02:09",
      "song_id": "BsSkjHIuVY9",
      "comment_source": "comment",
      "comment_date": "2024-10-01T12:55:36Z"
    },
    {
      "time": 4141,
      "original_time": "1:09:01",
      "song_id": "0dTcpXqsiVD",
      "comment_source": "comment",
      "comment_date": "2024-10-01T12:55:36Z"
    },
    {
      "time": 4607,
      "original_time": "1:16:47",
      "song_id": "ycpl020cXs1",
      "comment_source": "comment",
      "comment_date": "2024-10-01T12:55:36Z"
    },
    {
      "time": 5237,
      "original_time": "1:27:17",
      "song_id": "yRTEnAFNQj4",
      "comment_source": "comment",
      "comment_date": "2024-10-01T12:55:36Z"
    },
    {
      "time": 5745,
      "original_time": "1:35:45",
      "song_id": "VOmOMwqrCr3",
      "comment_source": "comment",
      "comment_date": "2024-10-01T12:55:36Z"
    },
    {
      "time": 6464,
      "original_time": "1:47:44",
      "song_id": "AYorCft04A2",
      "comment_source": "comment",
      "comment_date": "2024-10-01T12:55:36Z"
    },
    {
      "time": 6962,
      "original_time": "1:56:02",
      "song_id": "Shwys7i2XSL",
      "comment_source": "comment",
      "comment_date": "2024-10-01T12:55:36Z"
    },
    {
      "time": 7383,
      "original_time": "2:03:03",
      "song_id": "DamBH0PxiPw",
      "comment_source": "comment",
      "comment_date": "2024-10-01T12:55:36Z"
    }
  ]
}